[{"name":"Kusal Pereraʠ","runs":"2","balls":"6","fours":"0","sixes":"0"},{"name":"Kusal Pereraʠ","runs":"52","balls":"36","fours":"5","sixes":"1"},{"name":"Kusal Pereraʠ","runs":"30","balls":"34","fours":"4","sixes":"0"},{"name":"Kusal Pereraʠ","runs":"29","balls":"24","fours":"4","sixes":"0"},{"name":"Kusal Pereraʠ","runs":"29","balls":"24","fours":"4","sixes":"0"},{"name":"Kusal Pereraʠ","runs":"2","balls":"6","fours":"0","sixes":"0"},{"name":"Kusal Pereraʠ","runs":"29","balls":"24","fours":"4","sixes":"0"},{"name":"Kusal Pereraʠ","runs":"78","balls":"81","fours":"8","sixes":"0"},{"name":"Kusal Pereraʠ","runs":"64","balls":"51","fours":"8","sixes":"0"},{"name":"Kusal Pereraʠ","runs":"18","balls":"14","fours":"3","sixes":"0"},{"name":"Kusal Pereraʠ","runs":"78","balls":"81","fours":"8","sixes":"0"},{"name":"Kusal Pereraʠ","runs":"64","balls":"51","fours":"8","sixes":"0"},{"name":"Kusal Pereraʠ","runs":"78","balls":"81","fours":"8","sixes":"0"},{"name":"Kusal Pereraʠ","runs":"18","balls":"14","fours":"3","sixes":"0"},{"name":"Kusal Pereraʠ","runs":"2","balls":"6","fours":"0","sixes":"0"},{"name":"Kusal Pereraʠ","runs":"2","balls":"6","fours":"0","sixes":"0"},{"name":"Kusal Pereraʠ","runs":"29","balls":"24","fours":"4","sixes":"0"},{"name":"Kusal Pereraʠ","runs":"2","balls":"6","fours":"0","sixes":"0"},{"name":"Kusal Pereraʠ","runs":"18","balls":"14","fours":"3","sixes":"0"},{"name":"Kusal Pereraʠ","runs":"18","balls":"14","fours":"3","sixes":"0"},{"name":"Kusal Pereraʠ","runs":"64","balls":"51","fours":"8","sixes":"0"},{"name":"Kusal Pereraʠ","runs":"30","balls":"34","fours":"4","sixes":"0"},{"name":"Kusal Pereraʠ","runs":"29","balls":"24","fours":"4","sixes":"0"},{"name":"Kusal Pereraʠ","runs":"78","balls":"81","fours":"8","sixes":"0"},{"name":"Kusal Pereraʠ","runs":"18","balls":"14","fours":"3","sixes":"0"},{"name":"Kusal Pereraʠ","runs":"18","balls":"14","fours":"3","sixes":"0"},{"name":"Kusal Pereraʠ","runs":"30","balls":"34","fours":"4","sixes":"0"},{"name":"Kusal Pereraʠ","runs":"52","balls":"36","fours":"5","sixes":"1"},{"name":"Kusal Pereraʠ","runs":"30","balls":"34","fours":"4","sixes":"0"},{"name":"Kusal Pereraʠ","runs":"52","balls":"36","fours":"5","sixes":"1"},{"name":"Kusal Pereraʠ","runs":"2","balls":"6","fours":"0","sixes":"0"},{"name":"Kusal Pereraʠ","runs":"64","balls":"51","fours":"8","sixes":"0"},{"name":"Kusal Pereraʠ","runs":"52","balls":"36","fours":"5","sixes":"1"},{"name":"Kusal Pereraʠ","runs":"30","balls":"34","fours":"4","sixes":"0"},{"name":"Kusal Pereraʠ","runs":"52","balls":"36","fours":"5","sixes":"1"},{"name":"Kusal Pereraʠ","runs":"29","balls":"24","fours":"4","sixes":"0"},{"name":"Kusal Pereraʠ","runs":"30","balls":"34","fours":"4","sixes":"0"},{"name":"Kusal Pereraʠ","runs":"78","balls":"81","fours":"8","sixes":"0"},{"name":"Kusal Pereraʠ","runs":"78","balls":"81","fours":"8","sixes":"0"},{"name":"Kusal Pereraʠ","runs":"64","balls":"51","fours":"8","sixes":"0"},{"name":"Kusal Pereraʠ","runs":"64","balls":"51","fours":"8","sixes":"0"},{"name":"Kusal Pereraʠ","runs":"52","balls":"36","fours":"5","sixes":"1"}]