[{"name":"Dwaine Pretorius","runs":"1","balls":"1","fours":"0","sixes":"0"},{"name":"Dwaine Pretorius","runs":"1","balls":"1","fours":"0","sixes":"0"},{"name":"Dwaine Pretorius","runs":"1","balls":"1","fours":"0","sixes":"0"},{"name":"Dwaine Pretorius","runs":"1","balls":"1","fours":"0","sixes":"0"},{"name":"Dwaine Pretorius","runs":"1","balls":"1","fours":"0","sixes":"0"},{"name":"Dwaine Pretorius","runs":"2","balls":"5","fours":"0","sixes":"0"},{"name":"Dwaine Pretorius","runs":"2","balls":"5","fours":"0","sixes":"0"},{"name":"Dwaine Pretorius","runs":"2","balls":"5","fours":"0","sixes":"0"},{"name":"Dwaine Pretorius","runs":"1","balls":"1","fours":"0","sixes":"0"},{"name":"Dwaine Pretorius","runs":"2","balls":"5","fours":"0","sixes":"0"},{"name":"Dwaine Pretorius","runs":"2","balls":"5","fours":"0","sixes":"0"},{"name":"Dwaine Pretorius","runs":"2","balls":"5","fours":"0","sixes":"0"}]